async_couch/__init__.py
async_couch/clients/__init__.py
async_couch/clients/database/__init__.py
async_couch/clients/database/endpoints.py
async_couch/clients/database/models.py
async_couch/clients/database/responses.py
async_couch/clients/designs/__init__.py
async_couch/clients/designs/endpoints.py
async_couch/clients/designs/responses.py
async_couch/clients/documents/__init__.py
async_couch/clients/documents/endpoints.py
async_couch/clients/documents/responses.py
async_couch/exc.py
async_couch/http_clients/__init__.py
async_couch/http_clients/base_client.py
async_couch/http_clients/httpx_client.py
async_couch/types.py
async_couch/utils/__init__.py
async_couch/utils/content_types.py
async_couch-0.2.0.dist-info/AUTHORS.rst
async_couch-0.2.0.dist-info/LICENSE
async_couch-0.2.0.dist-info/METADATA
async_couch-0.2.0.dist-info/WHEEL
async_couch-0.2.0.dist-info/RECORD
