Metadata-Version: 2.1
Name: async-couch
Version: 0.2.0
Summary: Asynchronous client for CouchDB.
Home-page: https://github.com/symstu/async-couch/
License: MIT
Author: Maksym Stukalo
Author-email: stukalo.maksym@gmail.com
Requires-Python: >=3.11,<4.0
Classifier: License :: OSI Approved :: MIT License
Classifier: Operating System :: OS Independent
Classifier: Programming Language :: Python :: 3
Classifier: Programming Language :: Python :: 3.11
Classifier: Programming Language :: Python :: 3.12
Provides-Extra: orjson
Requires-Dist: anyio (>=4.4.0,<5.0.0)
Requires-Dist: httpx[brotli,http2] (>=0.27.0,<0.28.0)
Requires-Dist: orjson (>=3.10.6,<4.0.0) ; extra == "orjson"
Project-URL: Repository, https://github.com/symstu/async-couch/
